<?xml version='1.0' encoding='UTF-8'?>
<artifactory-file>
  <repoPath>
    <repoKey>libs-snapshot-local</repoKey>
    <path>pl/pandait/panda/0.0.2-SNAPSHOT/panda-0.0.2-20220224.092344-1.pom</path>
    <folder>false</folder>
  </repoPath>
  <name>panda-0.0.2-20220224.092344-1.pom</name>
  <created>1645694626287</created>
  <lastModified>1645694626266</lastModified>
  <size>4854</size>
  <additionalInfo>
    <createdBy>admin</createdBy>
    <modifiedBy>admin</modifiedBy>
    <lastUpdated>1645694626289</lastUpdated>
    <checksumsInfo>
      <checksums>
        <checksum>
          <type>sha1</type>
          <original>36b701618e174d826bf875aa8dd4dd9aacc4ef11</original>
          <actual>36b701618e174d826bf875aa8dd4dd9aacc4ef11</actual>
        </checksum>
        <checksum>
          <type>md5</type>
          <original>fd7ad8b6626a2c135590967015f01cca</original>
          <actual>fd7ad8b6626a2c135590967015f01cca</actual>
        </checksum>
        <checksum>
          <type>sha256</type>
          <original>NO_ORIG</original>
          <actual>d04f235f538c846d707693b733e959ada09a92a0901bd95f7708833df9a4134e</actual>
        </checksum>
      </checksums>
    </checksumsInfo>
  </additionalInfo>
</artifactory-file>